bitbnspy/__init__.py
bitbnspy/bitbns.py
bitbnspy-0.3.1.dist-info/LICENSE.txt
bitbnspy-0.3.1.dist-info/METADATA
bitbnspy-0.3.1.dist-info/WHEEL
bitbnspy-0.3.1.dist-info/top_level.txt
bitbnspy-0.3.1.dist-info/RECORD
