Metadata-Version: 2.1
Name: bitbnspy
Version: 0.3.1
Summary: This project is designed to assist you make your own projects that interact with the Bitbns API. This project seeks to have complete API coverage and WebSockets
Home-page: https://github.com/bitbns-official/bitbnspy
Author: Prashant Singh
Author-email: prashant@buyhatke.com
License: MIT
Keywords: python,bitbns,DEFI,crypto,btc,eth,neo,orderbook,crypto trading,bitbns api,margin trading,partner apis,payment gatway,fips,futures
Classifier: Development Status :: 4 - Beta
Classifier: Intended Audience :: Developers
Classifier: Topic :: Software Development :: Build Tools
Classifier: License :: OSI Approved :: MIT License
Classifier: Programming Language :: Python :: 3.8
Classifier: Programming Language :: Python :: 3.7
Classifier: Programming Language :: Python :: 3.6
Requires-Python: >=3.6
License-File: LICENSE.txt
Requires-Dist: bidict (==0.21.2)
Requires-Dist: certifi (==2021.5.30)
Requires-Dist: chardet (==4.0.0)
Requires-Dist: idna (==2.10)
Requires-Dist: python-engineio (==4.2.0)
Requires-Dist: python-socketio (==5.3.0)
Requires-Dist: requests (==2.25.1)
Requires-Dist: urllib3 (==1.26.5)
Requires-Dist: websocket-client (==1.1.0)
